toposkg/__init__.py
toposkg/toposkg_lib_core.py
toposkg/toposkg_lib_entity_linking.py
toposkg/toposkg_lib_fc.py
toposkg/toposkg_lib_metadata.py
toposkg/toposkg_lib_translate.py
toposkg/utils.py
toposkg/converter/__init__.py
toposkg/converter/toposkg_lib_converter.py
toposkg/converter/toposkg_lib_csv_converter.py
toposkg/converter/toposkg_lib_geojson_converter.py
toposkg/converter/toposkg_lib_gml_converter.py
toposkg/converter/toposkg_lib_json_converter.py
toposkg/converter/toposkg_lib_kml_converter.py
toposkg/converter/toposkg_lib_shapefile_converter.py
toposkg/converter/toposkg_lib_xml_converter.py
toposkg/converter/rml/__init__.py
toposkg/converter/rml/toposkg_lib_csv_mapping_generator.py
toposkg/converter/rml/toposkg_lib_default_mapping_generator.py
toposkg/converter/rml/toposkg_lib_geojson_mapping_generator.py
toposkg/converter/rml/toposkg_lib_json_mapping_generator.py
toposkg/converter/rml/toposkg_lib_mapping_builder.py
toposkg/converter/rml/toposkg_lib_rml_module.py
toposkg/converter/rml/toposkg_lib_triples_map.py
toposkg/converter/rml/toposkg_lib_xml_mapping_generator.py
toposkg/jar_libs/DuplicateGeometryRemover-1.0-SNAPSHOT.jar
toposkg/jar_libs/geospatialinterlinking-1.0-SNAPSHOT-jar-with-dependencies.jar
toposkg/scripts/materialization.sh
toposkg/scripts/tsv_to_csv.py
toposkg-0.3.2.dist-info/METADATA
toposkg-0.3.2.dist-info/WHEEL
toposkg-0.3.2.dist-info/top_level.txt
toposkg-0.3.2.dist-info/RECORD
