Metadata-Version: 2.4
Name: toposkg
Version: 0.3.2
Summary: A Python interface to the ToposKG knowledge graph generation pipeline.
Author-email: Sergios-Anestis Kefalidis <skefalidis@di.uoa.gr>, Kostas Plas <kplas@di.uoa.gr>
License: MIT
Requires-Python: >=3.10
Requires-Dist: fsspec
Requires-Dist: pyjedai
Requires-Dist: pandas
Requires-Dist: rich
Requires-Dist: geopandas
Requires-Dist: geojson
Requires-Dist: shapely
Requires-Dist: fiona
Requires-Dist: six
Requires-Dist: pyproj
Requires-Dist: morph_kgc
Provides-Extra: tl
Requires-Dist: unsloth; extra == "tl"
Provides-Extra: fc
Requires-Dist: openai; extra == "fc"
Provides-Extra: full
Requires-Dist: openai; extra == "full"
Requires-Dist: unsloth; extra == "full"
